onnxruntime_noopenmp-1.6.0.data/purelib/onnxruntime/LICENSE
onnxruntime_noopenmp-1.6.0.data/purelib/onnxruntime/Privacy.md
onnxruntime_noopenmp-1.6.0.data/purelib/onnxruntime/ThirdPartyNotices.txt
onnxruntime_noopenmp-1.6.0.data/purelib/onnxruntime/__init__.py
onnxruntime_noopenmp-1.6.0.data/purelib/onnxruntime/backend/__init__.py
onnxruntime_noopenmp-1.6.0.data/purelib/onnxruntime/backend/backend.py
onnxruntime_noopenmp-1.6.0.data/purelib/onnxruntime/backend/backend_rep.py
onnxruntime_noopenmp-1.6.0.data/purelib/onnxruntime/capi/__init__.py
onnxruntime_noopenmp-1.6.0.data/purelib/onnxruntime/capi/_ld_preload.py
onnxruntime_noopenmp-1.6.0.data/purelib/onnxruntime/capi/_pybind_state.py
onnxruntime_noopenmp-1.6.0.data/purelib/onnxruntime/capi/onnxruntime_inference_collection.py
onnxruntime_noopenmp-1.6.0.data/purelib/onnxruntime/capi/onnxruntime_pybind11_state.pyd
onnxruntime_noopenmp-1.6.0.data/purelib/onnxruntime/capi/onnxruntime_validation.py
onnxruntime_noopenmp-1.6.0.data/purelib/onnxruntime/capi/training/__init__.py
onnxruntime_noopenmp-1.6.0.data/purelib/onnxruntime/datasets/__init__.py
onnxruntime_noopenmp-1.6.0.data/purelib/onnxruntime/datasets/logreg_iris.onnx
onnxruntime_noopenmp-1.6.0.data/purelib/onnxruntime/datasets/mul_1.onnx
onnxruntime_noopenmp-1.6.0.data/purelib/onnxruntime/datasets/sigmoid.onnx
onnxruntime_noopenmp-1.6.0.data/purelib/onnxruntime/quantization/__init__.py
onnxruntime_noopenmp-1.6.0.data/purelib/onnxruntime/quantization/calibrate.py
onnxruntime_noopenmp-1.6.0.data/purelib/onnxruntime/quantization/onnx_model.py
onnxruntime_noopenmp-1.6.0.data/purelib/onnxruntime/quantization/onnx_quantizer.py
onnxruntime_noopenmp-1.6.0.data/purelib/onnxruntime/quantization/quant_utils.py
onnxruntime_noopenmp-1.6.0.data/purelib/onnxruntime/quantization/quantize.py
onnxruntime_noopenmp-1.6.0.data/purelib/onnxruntime/quantization/registry.py
onnxruntime_noopenmp-1.6.0.data/purelib/onnxruntime/quantization/operators/__init__.py
onnxruntime_noopenmp-1.6.0.dist-info/METADATA
onnxruntime_noopenmp-1.6.0.dist-info/WHEEL
onnxruntime_noopenmp-1.6.0.dist-info/entry_points.txt
onnxruntime_noopenmp-1.6.0.dist-info/top_level.txt
onnxruntime_noopenmp-1.6.0.dist-info/RECORD
